youtbe/__init__.py
youtbe/base.py
youtbe-1.0.1.dist-info/METADATA
youtbe-1.0.1.dist-info/WHEEL
youtbe-1.0.1.dist-info/top_level.txt
youtbe-1.0.1.dist-info/RECORD
