Metadata-Version: 2.1
Name: youtbe
Version: 1.0.1
Summary: Package to Scrap Stats from Youtube Video
Author: vardxg
Author-email: <dev@vardxg.com>
Keywords: python,video,stats,video stats
Classifier: Development Status :: 1 - Planning
Classifier: Intended Audience :: Developers
Classifier: Programming Language :: Python :: 3
Classifier: Operating System :: Unix
Classifier: Operating System :: MacOS :: MacOS X
Classifier: Operating System :: Microsoft :: Windows
Requires-Dist: vardxg
Requires-Dist: colorama
Requires-Dist: requests
